Metadata-Version: 2.1
Name: pdf-utils
Version: 0.1.1
Summary: tools for reading and processing pdf content
Home-page: https://bitbucket.kendaya.net/projects/KXLAB/repos/pdf-tools/
Author: Kendaxa
Author-email: develop@kendaxa.com
License: UNKNOWN
Platform: UNKNOWN
Classifier: Development Status :: 3 - Alpha
Classifier: Intended Audience :: Developers
Classifier: Topic :: Software Development :: Build Tools
Classifier: Programming Language :: Python :: 3
Classifier: Programming Language :: Python :: 3.6
Classifier: Programming Language :: Python :: 3.7
Classifier: Programming Language :: Python :: 3.8
Requires-Python: >=3.6
